pyinno_setup/__init__.py
pyinno_setup/inno.py
pyinno_setup/runit.py
pyinno_setup/data/template.iss
pyinno_setup/libs/Inno6/Compil32.exe
pyinno_setup/libs/Inno6/Default.isl
pyinno_setup/libs/Inno6/ISCC.exe
pyinno_setup/libs/Inno6/ISCmplr.dll
pyinno_setup/libs/Inno6/ISPP.chm
pyinno_setup/libs/Inno6/ISPP.dll
pyinno_setup/libs/Inno6/ISPPBuiltins.iss
pyinno_setup/libs/Inno6/ISetup-dark.chm
pyinno_setup/libs/Inno6/ISetup.chm
pyinno_setup/libs/Inno6/Setup.e32
pyinno_setup/libs/Inno6/SetupClassicIcon.ico
pyinno_setup/libs/Inno6/SetupLdr.e32
pyinno_setup/libs/Inno6/WizClassicImage-IS.bmp
pyinno_setup/libs/Inno6/WizClassicImage.bmp
pyinno_setup/libs/Inno6/WizClassicSmallImage-IS.bmp
pyinno_setup/libs/Inno6/WizClassicSmallImage.bmp
pyinno_setup/libs/Inno6/isbunzip.dll
pyinno_setup/libs/Inno6/isbzip.dll
pyinno_setup/libs/Inno6/isfaq.url
pyinno_setup/libs/Inno6/islzma.dll
pyinno_setup/libs/Inno6/islzma32.exe
pyinno_setup/libs/Inno6/islzma64.exe
pyinno_setup/libs/Inno6/isscint.dll
pyinno_setup/libs/Inno6/isunzlib.dll
pyinno_setup/libs/Inno6/iszlib.dll
pyinno_setup/libs/Inno6/license.txt
pyinno_setup/libs/Inno6/unins000.dat
pyinno_setup/libs/Inno6/unins000.exe
pyinno_setup/libs/Inno6/unins000.msg
pyinno_setup/libs/Inno6/whatsnew.htm
pyinno_setup/libs/Inno6/Examples/64Bit.iss
pyinno_setup/libs/Inno6/Examples/64BitThreeArch.iss
pyinno_setup/libs/Inno6/Examples/64BitTwoArch.iss
pyinno_setup/libs/Inno6/Examples/AllPagesExample.iss
pyinno_setup/libs/Inno6/Examples/CodeAutomation.iss
pyinno_setup/libs/Inno6/Examples/CodeAutomation2.iss
pyinno_setup/libs/Inno6/Examples/CodeClasses.iss
pyinno_setup/libs/Inno6/Examples/CodeDlg.iss
pyinno_setup/libs/Inno6/Examples/CodeDll.iss
pyinno_setup/libs/Inno6/Examples/CodeDownloadFiles.iss
pyinno_setup/libs/Inno6/Examples/CodeExample1.iss
pyinno_setup/libs/Inno6/Examples/CodePrepareToInstall.iss
pyinno_setup/libs/Inno6/Examples/Components.iss
pyinno_setup/libs/Inno6/Examples/Example1.iss
pyinno_setup/libs/Inno6/Examples/Example2.iss
pyinno_setup-0.0.6.dist-info/licenses/LICENSE
pyinno_setup-0.0.6.dist-info/METADATA
pyinno_setup-0.0.6.dist-info/WHEEL
pyinno_setup-0.0.6.dist-info/top_level.txt
pyinno_setup-0.0.6.dist-info/RECORD
