Metadata-Version: 2.4
Name: pyinno_setup
Version: 0.0.6
Summary: module for creating installable exe from iss file using innosetup compiler
Author-email: keralaboy <keralaboypypi@keralaboy.anonaddy.com>
License-Expression: MIT
Project-URL: Homepage, https://github.com/its-me-abi/pyinno_setup
Keywords: compiler,inno setup,exe,installer,generate
Classifier: Development Status :: 4 - Beta
Classifier: Programming Language :: Python
Requires-Python: >=3.6
License-File: LICENSE
Requires-Dist: pyargman>=0.0.4
Dynamic: license-file
